<?xml version="1.0" encoding="UTF-8"?>
<model>

<!--START_p382852-->
<item name="p382852" caption="Редуктор, трансмиссия" key="" virtual="false" user-def="true" description="" super="params *" ag-id="1791" ag-hash="2129513400"></item>
<!--END_p382852-->

<!--START_p383226-->
<item name="p383226" caption="Пробки двигателя и редуктора" key="" virtual="false" user-def="true" description="" super="params *" ag-id="1792" ag-hash="2129537336"></item>
<!--END_p383226-->

<!--START_p383238-->
<item name="p383238" caption="Подшипники" key="" virtual="false" user-def="true" description="" super="params *" ag-id="1793" ag-hash="2129537369"></item>
<!--END_p383238-->

<!--START_p383355-->
<item name="p383355" caption="Установочные к-ты винтов" key="" virtual="false" user-def="true" description="" super="params *" ag-id="1794" ag-hash="2129538389"></item>
<!--END_p383355-->

<!--START_p383364-->
<item name="p383364" caption="Комплекты для запуска и зарядки АКБ" key="" virtual="false" user-def="true" description="" super="params *" ag-id="1795" ag-hash="2129538419"></item>
<!--END_p383364-->

<!--START_p383372-->
<item name="p383372" caption="Ремкомплекты блока" key="" virtual="false" user-def="true" description="" super="params *" ag-id="1796" ag-hash="2129538448"></item>
<!--END_p383372-->

<!--START_p383396-->
<item name="p383396" caption="Крепежные элементы" key="" virtual="false" user-def="true" description="" super="params *" ag-id="1797" ag-hash="2129538514"></item>
<!--END_p383396-->

<!--START_p383543-->
<item name="p383543" caption="Комплекты подключения д/у" key="" virtual="false" user-def="true" description="" super="params *" ag-id="1798" ag-hash="2129540278"></item>
<!--END_p383543-->

<!--START_p383569-->
<item name="p383569" caption="Топливная система" key="" virtual="false" user-def="true" description="" super="params *" ag-id="1799" ag-hash="2129540346"></item>
<!--END_p383569-->

<!--START_p383713-->
<item name="p383713" caption="Электрооборудование" key="" virtual="false" user-def="true" description="" super="params *" ag-id="1800" ag-hash="2129542107">
	<parameter name="proizvoditel" caption="Производитель" type="string" multiple="false" domain="" format="" ag-id="0" ag-hash="235196415" description="" owner-id="0" virtual="false" hidden="false"></parameter>
	<parameter name="originalnyi_kod" caption="Оригинальный код" type="string" multiple="false" domain="" format="" ag-id="0" ag-hash="281232590" description="" owner-id="0" virtual="false" hidden="false"></parameter>
</item>
<!--END_p383713-->

<!--START_p383838-->
<item name="p383838" caption="Ремкомплекты редуктора" key="" virtual="false" user-def="true" description="" super="params *" ag-id="1801" ag-hash="2129543135"></item>
<!--END_p383838-->

<!--START_p383890-->
<item name="p383890" caption="Прокладки" key="" virtual="false" user-def="true" description="" super="params *" ag-id="1802" ag-hash="2129543313"></item>
<!--END_p383890-->

<!--START_p384102-->
<item name="p384102" caption="Сальники" key="" virtual="false" user-def="true" description="" super="params *" ag-id="1803" ag-hash="2129566100"></item>
<!--END_p384102-->

<!--START_p384206-->
<item name="p384206" caption="Приборы контроля" key="" virtual="false" user-def="true" description="" super="params *" ag-id="1804" ag-hash="2129567065">
	<parameter name="proizvoditel" caption="Производитель" type="string" multiple="false" domain="" format="" ag-id="0" ag-hash="235196415" description="" owner-id="0" virtual="false" hidden="false"></parameter>
	<parameter name="originalnyi_kod" caption="Оригинальный код" type="string" multiple="false" domain="" format="" ag-id="0" ag-hash="281232590" description="" owner-id="0" virtual="false" hidden="false"></parameter>
</item>
<!--END_p384206-->

<!--START_p384270-->
<item name="p384270" caption="Блок двигателя" key="" virtual="false" user-def="true" description="" super="params *" ag-id="1805" ag-hash="2129567276"></item>
<!--END_p384270-->

<!--START_p384602-->
<item name="p384602" caption="Гребные винты" key="" virtual="false" user-def="true" description="" super="params *" ag-id="1806" ag-hash="2129570905">
	<parameter name="chetyrehtaktnye_motory" caption="Четырехтактные моторы" type="string" multiple="false" domain="" format="" ag-id="0" ag-hash="-591936785" description="" owner-id="0" virtual="false" hidden="false"></parameter>
	<parameter name="k_vo_lopastei" caption="К-во лопастей" type="integer" multiple="false" domain="" format="" ag-id="0" ag-hash="-1512698773" description="" owner-id="0" virtual="false" hidden="false"></parameter>
	<parameter name="diametr_vinta" caption="Диаметр винта" type="string" multiple="false" domain="" format="" ag-id="0" ag-hash="-1991023141" description="&quot;" owner-id="0" virtual="false" hidden="false"></parameter>
	<parameter name="shag_vinta" caption="Шаг винта" type="string" multiple="false" domain="" format="" ag-id="0" ag-hash="1183539140" description="&quot;" owner-id="0" virtual="false" hidden="false"></parameter>
	<parameter name="material" caption="Материал" type="string" multiple="false" domain="" format="" ag-id="0" ag-hash="299066663" description="" owner-id="0" virtual="false" hidden="false"></parameter>
	<parameter name="vraschenie" caption="Вращение" type="string" multiple="false" domain="" format="" ag-id="0" ag-hash="1860900568" description="" owner-id="0" virtual="false" hidden="false"></parameter>
	<parameter name="posadka_na_val" caption="Посадка на вал" type="string" multiple="false" domain="" format="" ag-id="0" ag-hash="1066570247" description="" owner-id="0" virtual="false" hidden="false"></parameter>
	<parameter name="proizvoditel" caption="Производитель" type="string" multiple="false" domain="" format="" ag-id="0" ag-hash="235196415" description="" owner-id="0" virtual="false" hidden="false"></parameter>
	<parameter name="originalnyi_kod" caption="Оригинальный код" type="string" multiple="false" domain="" format="" ag-id="0" ag-hash="281232590" description="" owner-id="0" virtual="false" hidden="false"></parameter>
	<parameter name="dvuhtaktnye_motory" caption="Двухтактные моторы" type="string" multiple="false" domain="" format="" ag-id="0" ag-hash="1620886916" description="" owner-id="0" virtual="false" hidden="false"></parameter>
	<parameter name="modifikatsiya_vinta" caption="Модификация винта" type="string" multiple="false" domain="" format="" ag-id="0" ag-hash="-1298502629" description="" owner-id="0" virtual="false" hidden="false"></parameter>
	<parameter name="osobennosti" caption="Особенности" type="string" multiple="false" domain="" format="" ag-id="0" ag-hash="-86809817" description="" owner-id="0" virtual="false" hidden="false"></parameter>
</item>
<!--END_p384602-->

<!--START_p384915-->
<item name="p384915" caption="Дейдвуд, подвеска" key="" virtual="false" user-def="true" description="" super="params *" ag-id="1807" ag-hash="2129573822"></item>
<!--END_p384915-->

<!--START_p385058-->
<item name="p385058" caption="Управление (пульты д/у)" key="" virtual="false" user-def="true" description="" super="params *" ag-id="1808" ag-hash="2129595091">
	<parameter name="proizvoditel" caption="Производитель" type="string" multiple="false" domain="" format="" ag-id="0" ag-hash="235196415" description="" owner-id="0" virtual="false" hidden="false"></parameter>
	<parameter name="originalnyi_kod" caption="Оригинальный код" type="string" multiple="false" domain="" format="" ag-id="0" ag-hash="281232590" description="" owner-id="0" virtual="false" hidden="false"></parameter>
</item>
<!--END_p385058-->

<!--START_p385151-->
<item name="p385151" caption="Система охлаждения" key="" virtual="false" user-def="true" description="" super="params *" ag-id="1809" ag-hash="2129596045"></item>
<!--END_p385151-->

<!--START_p385851-->
<item name="p385851" caption="Серия BTG" key="" virtual="false" user-def="true" description="" super="params *" ag-id="1810" ag-hash="2129602772"></item>
<!--END_p385851-->

<!--START_p382664-->
<item name="p382664" caption="Моторы Suzuki 2,5...30 л.с." key="" virtual="false" user-def="true" description="" super="params *" ag-id="1786" ag-hash="2129511511">
	<parameter name="taktnost" caption="Тактность" type="integer" multiple="false" domain="" format="" ag-id="0" ag-hash="-630085256" description="-тактный" owner-id="0" virtual="false" hidden="false"></parameter>
	<parameter name="moschnost" caption="Мощность" type="double" multiple="false" domain="" format="" ag-id="0" ag-hash="-1643161576" description="л.с." owner-id="0" virtual="false" hidden="false"></parameter>
	<parameter name="kol_vo_tsilindrov" caption="Кол-во цилиндров" type="integer" multiple="false" domain="" format="" ag-id="0" ag-hash="-1202498357" description="" owner-id="0" virtual="false" hidden="false"></parameter>
	<parameter name="obem_dvigatelya" caption="Объем двигателя" type="integer" multiple="false" domain="" format="" ag-id="0" ag-hash="1653502678" description="см³" owner-id="0" virtual="false" hidden="false"></parameter>
	<parameter name="tip_topliva" caption="Тип топлива" type="string" multiple="false" domain="" format="" ag-id="0" ag-hash="-799384551" description="" owner-id="0" virtual="false" hidden="false"></parameter>
	<parameter name="podacha_topliva" caption="Подача топлива" type="string" multiple="false" domain="" format="" ag-id="0" ag-hash="-1652185378" description="" owner-id="0" virtual="false" hidden="false"></parameter>
	<parameter name="sistema_smazki" caption="Система смазки" type="string" multiple="false" domain="" format="" ag-id="0" ag-hash="-2129155730" description="" owner-id="0" virtual="false" hidden="false"></parameter>
	<parameter name="diapazon_maks__oborotov" caption="Диапазон макс. оборотов" type="string" multiple="false" domain="" format="" ag-id="0" ag-hash="2134028465" description="" owner-id="0" virtual="false" hidden="false"></parameter>
	<parameter name="upravlenie" caption="Управление" type="string" multiple="false" domain="" format="" ag-id="0" ag-hash="-1602156091" description="" owner-id="0" virtual="false" hidden="false"></parameter>
	<parameter name="zapusk" caption="Запуск" type="string" multiple="false" domain="" format="" ag-id="0" ag-hash="-709176636" description="" owner-id="0" virtual="false" hidden="false"></parameter>
	<parameter name="podem" caption="Подъем" type="string" multiple="false" domain="" format="" ag-id="0" ag-hash="106840493" description="" owner-id="0" virtual="false" hidden="false"></parameter>
	<parameter name="tranets_plavsredstva" caption="Транец плавсредства" type="integer" multiple="false" domain="" format="" ag-id="0" ag-hash="1594059553" description="мм" owner-id="0" virtual="false" hidden="false"></parameter>
	<parameter name="svecha_zagiganiya_ngk" caption="Свеча зажигания (NGK)" type="string" multiple="false" domain="" format="" ag-id="0" ag-hash="-101941410" description="" owner-id="0" virtual="false" hidden="false"></parameter>
	<parameter name="toplivnyi_bak" caption="Топливный бак" type="double" multiple="false" domain="" format="" ag-id="0" ag-hash="-576195929" description="л" owner-id="0" virtual="false" hidden="false"></parameter>
	<parameter name="vraschenie_vinta" caption="Вращение винта" type="string" multiple="false" domain="" format="" ag-id="0" ag-hash="1724986273" description="" owner-id="0" virtual="false" hidden="false"></parameter>
	<parameter name="reduktsiya" caption="Редукция" type="string" multiple="false" domain="" format="" ag-id="0" ag-hash="-971909173" description="" owner-id="0" virtual="false" hidden="false"></parameter>
	<parameter name="shtatnyi_vint" caption="Штатный винт" type="string" multiple="false" domain="" format="" ag-id="0" ag-hash="-676308340" description="" owner-id="0" virtual="false" hidden="false"></parameter>
	<parameter name="reduktor" caption="Редуктор" type="integer" multiple="false" domain="" format="" ag-id="0" ag-hash="-765256432" description="мл" owner-id="0" virtual="false" hidden="false"></parameter>
	<parameter name="karter" caption="Картер" type="integer" multiple="false" domain="" format="" ag-id="0" ag-hash="-1138555707" description="мл" owner-id="0" virtual="false" hidden="false"></parameter>
	<parameter name="ves" caption="Вес" type="double" multiple="false" domain="" format="" ag-id="0" ag-hash="116644" description="кг" owner-id="0" virtual="false" hidden="false"></parameter>
	<parameter name="garantiya" caption="Гарантия" type="integer" multiple="false" domain="" format="" ag-id="0" ag-hash="1043041986" description="года" owner-id="0" virtual="false" hidden="false"></parameter>
	<parameter name="razmer_sm" caption="Размер, см" type="string" multiple="false" domain="" format="" ag-id="0" ag-hash="1481142986" description="" owner-id="0" virtual="false" hidden="false"></parameter>
	<parameter name="ves_brutto" caption="Вес брутто" type="integer" multiple="false" domain="" format="" ag-id="0" ag-hash="304704165" description="кг" owner-id="0" virtual="false" hidden="false"></parameter>
	<parameter name="obem" caption="Объем" type="double" multiple="false" domain="" format="" ag-id="0" ag-hash="3404219" description="м³" owner-id="0" virtual="false" hidden="false"></parameter>
	<parameter name="proizvoditel" caption="Производитель" type="string" multiple="false" domain="" format="" ag-id="0" ag-hash="235196415" description="" owner-id="0" virtual="false" hidden="false"></parameter>
	<parameter name="strana" caption="Страна" type="string" multiple="false" domain="" format="" ag-id="0" ag-hash="-891993597" description="" owner-id="0" virtual="false" hidden="false"></parameter>
	<parameter name="generator" caption="Генератор" type="string" multiple="false" domain="" format="" ag-id="0" ag-hash="286956243" description="" owner-id="0" virtual="false" hidden="false"></parameter>
	<parameter name="diapazon_vintov" caption="Диапазон винтов" type="string" multiple="false" domain="" format="" ag-id="0" ag-hash="-1377350221" description="" owner-id="0" virtual="false" hidden="false"></parameter>
	<parameter name="zadnii_hod" caption="Задний ход" type="string" multiple="false" domain="" format="" ag-id="0" ag-hash="-1594739249" description="" owner-id="0" virtual="false" hidden="false"></parameter>
	<parameter name="rekomenduemyi_akkumulyator" caption="Рекомендуемый аккумулятор" type="string" multiple="false" domain="" format="" ag-id="0" ag-hash="378721238" description="Ah" owner-id="0" virtual="false" hidden="false"></parameter>
</item>
<!--END_p382664-->

<!--START_p382721-->
<item name="p382721" caption="Снятые с производства" key="" virtual="false" user-def="true" description="" super="params *" ag-id="1787" ag-hash="2129512345">
	<parameter name="taktnost" caption="Тактность" type="integer" multiple="false" domain="" format="" ag-id="0" ag-hash="-630085256" description="-тактный" owner-id="0" virtual="false" hidden="false"></parameter>
	<parameter name="moschnost" caption="Мощность" type="double" multiple="false" domain="" format="" ag-id="0" ag-hash="-1643161576" description="л.с." owner-id="0" virtual="false" hidden="false"></parameter>
	<parameter name="kol_vo_tsilindrov" caption="Кол-во цилиндров" type="integer" multiple="false" domain="" format="" ag-id="0" ag-hash="-1202498357" description="" owner-id="0" virtual="false" hidden="false"></parameter>
	<parameter name="obem_dvigatelya" caption="Объем двигателя" type="integer" multiple="false" domain="" format="" ag-id="0" ag-hash="1653502678" description="см³" owner-id="0" virtual="false" hidden="false"></parameter>
	<parameter name="tip_topliva" caption="Тип топлива" type="string" multiple="false" domain="" format="" ag-id="0" ag-hash="-799384551" description="" owner-id="0" virtual="false" hidden="false"></parameter>
	<parameter name="podacha_topliva" caption="Подача топлива" type="string" multiple="false" domain="" format="" ag-id="0" ag-hash="-1652185378" description="" owner-id="0" virtual="false" hidden="false"></parameter>
	<parameter name="sistema_smazki" caption="Система смазки" type="string" multiple="false" domain="" format="" ag-id="0" ag-hash="-2129155730" description="" owner-id="0" virtual="false" hidden="false"></parameter>
	<parameter name="diapazon_maks__oborotov" caption="Диапазон макс. оборотов" type="string" multiple="false" domain="" format="" ag-id="0" ag-hash="2134028465" description="" owner-id="0" virtual="false" hidden="false"></parameter>
	<parameter name="generator" caption="Генератор" type="string" multiple="false" domain="" format="" ag-id="0" ag-hash="286956243" description="" owner-id="0" virtual="false" hidden="false"></parameter>
	<parameter name="rekomenduemyi_akkumulyator" caption="Рекомендуемый аккумулятор" type="string" multiple="false" domain="" format="" ag-id="0" ag-hash="378721238" description="Ah" owner-id="0" virtual="false" hidden="false"></parameter>
	<parameter name="upravlenie" caption="Управление" type="string" multiple="false" domain="" format="" ag-id="0" ag-hash="-1602156091" description="" owner-id="0" virtual="false" hidden="false"></parameter>
	<parameter name="zapusk" caption="Запуск" type="string" multiple="false" domain="" format="" ag-id="0" ag-hash="-709176636" description="" owner-id="0" virtual="false" hidden="false"></parameter>
	<parameter name="podem" caption="Подъем" type="string" multiple="false" domain="" format="" ag-id="0" ag-hash="106840493" description="" owner-id="0" virtual="false" hidden="false"></parameter>
	<parameter name="tranets_plavsredstva" caption="Транец плавсредства" type="integer" multiple="false" domain="" format="" ag-id="0" ag-hash="1594059553" description="мм" owner-id="0" virtual="false" hidden="false"></parameter>
	<parameter name="svecha_zagiganiya_ngk" caption="Свеча зажигания (NGK)" type="string" multiple="false" domain="" format="" ag-id="0" ag-hash="-101941410" description="" owner-id="0" virtual="false" hidden="false"></parameter>
	<parameter name="toplivnyi_bak" caption="Топливный бак" type="double" multiple="false" domain="" format="" ag-id="0" ag-hash="-576195929" description="л" owner-id="0" virtual="false" hidden="false"></parameter>
	<parameter name="vraschenie_vinta" caption="Вращение винта" type="string" multiple="false" domain="" format="" ag-id="0" ag-hash="1724986273" description="" owner-id="0" virtual="false" hidden="false"></parameter>
	<parameter name="reduktsiya" caption="Редукция" type="string" multiple="false" domain="" format="" ag-id="0" ag-hash="-971909173" description="" owner-id="0" virtual="false" hidden="false"></parameter>
	<parameter name="shtatnyi_vint" caption="Штатный винт" type="string" multiple="false" domain="" format="" ag-id="0" ag-hash="-676308340" description="" owner-id="0" virtual="false" hidden="false"></parameter>
	<parameter name="diapazon_vintov" caption="Диапазон винтов" type="string" multiple="false" domain="" format="" ag-id="0" ag-hash="-1377350221" description="" owner-id="0" virtual="false" hidden="false"></parameter>
	<parameter name="zadnii_hod" caption="Задний ход" type="string" multiple="false" domain="" format="" ag-id="0" ag-hash="-1594739249" description="" owner-id="0" virtual="false" hidden="false"></parameter>
	<parameter name="reduktor" caption="Редуктор" type="integer" multiple="false" domain="" format="" ag-id="0" ag-hash="-765256432" description="мл" owner-id="0" virtual="false" hidden="false"></parameter>
	<parameter name="ves" caption="Вес" type="double" multiple="false" domain="" format="" ag-id="0" ag-hash="116644" description="кг" owner-id="0" virtual="false" hidden="false"></parameter>
	<parameter name="garantiya" caption="Гарантия" type="integer" multiple="false" domain="" format="" ag-id="0" ag-hash="1043041986" description="года" owner-id="0" virtual="false" hidden="false"></parameter>
	<parameter name="razmer_sm" caption="Размер, см" type="string" multiple="false" domain="" format="" ag-id="0" ag-hash="1481142986" description="" owner-id="0" virtual="false" hidden="false"></parameter>
	<parameter name="ves_brutto" caption="Вес брутто" type="integer" multiple="false" domain="" format="" ag-id="0" ag-hash="304704165" description="кг" owner-id="0" virtual="false" hidden="false"></parameter>
	<parameter name="obem" caption="Объем" type="double" multiple="false" domain="" format="" ag-id="0" ag-hash="3404219" description="м³" owner-id="0" virtual="false" hidden="false"></parameter>
	<parameter name="proizvoditel" caption="Производитель" type="string" multiple="false" domain="" format="" ag-id="0" ag-hash="235196415" description="" owner-id="0" virtual="false" hidden="false"></parameter>
	<parameter name="strana" caption="Страна" type="string" multiple="false" domain="" format="" ag-id="0" ag-hash="-891993597" description="" owner-id="0" virtual="false" hidden="false"></parameter>
	<parameter name="karter" caption="Картер" type="integer" multiple="false" domain="" format="" ag-id="0" ag-hash="-1138555707" description="мл" owner-id="0" virtual="false" hidden="false"></parameter>
</item>
<!--END_p382721-->

<!--START_p382750-->
<item name="p382750" caption="Моторы Suzuki 40...100 л.с." key="" virtual="false" user-def="true" description="" super="params *" ag-id="1788" ag-hash="2129512437">
	<parameter name="taktnost" caption="Тактность" type="integer" multiple="false" domain="" format="" ag-id="0" ag-hash="-630085256" description="-тактный" owner-id="0" virtual="false" hidden="false"></parameter>
	<parameter name="moschnost" caption="Мощность" type="integer" multiple="false" domain="" format="" ag-id="0" ag-hash="-1643161576" description="л.с." owner-id="0" virtual="false" hidden="false"></parameter>
	<parameter name="kol_vo_tsilindrov" caption="Кол-во цилиндров" type="integer" multiple="false" domain="" format="" ag-id="0" ag-hash="-1202498357" description="" owner-id="0" virtual="false" hidden="false"></parameter>
	<parameter name="obem_dvigatelya" caption="Объем двигателя" type="integer" multiple="false" domain="" format="" ag-id="0" ag-hash="1653502678" description="см³" owner-id="0" virtual="false" hidden="false"></parameter>
	<parameter name="tip_topliva" caption="Тип топлива" type="string" multiple="false" domain="" format="" ag-id="0" ag-hash="-799384551" description="" owner-id="0" virtual="false" hidden="false"></parameter>
	<parameter name="podacha_topliva" caption="Подача топлива" type="string" multiple="false" domain="" format="" ag-id="0" ag-hash="-1652185378" description="" owner-id="0" virtual="false" hidden="false"></parameter>
	<parameter name="sistema_smazki" caption="Система смазки" type="string" multiple="false" domain="" format="" ag-id="0" ag-hash="-2129155730" description="" owner-id="0" virtual="false" hidden="false"></parameter>
	<parameter name="diapazon_maks__oborotov" caption="Диапазон макс. оборотов" type="string" multiple="false" domain="" format="" ag-id="0" ag-hash="2134028465" description="" owner-id="0" virtual="false" hidden="false"></parameter>
	<parameter name="generator" caption="Генератор" type="string" multiple="false" domain="" format="" ag-id="0" ag-hash="286956243" description="" owner-id="0" virtual="false" hidden="false"></parameter>
	<parameter name="rekomenduemyi_akkumulyator" caption="Рекомендуемый аккумулятор" type="integer" multiple="false" domain="" format="" ag-id="0" ag-hash="378721238" description="Ah" owner-id="0" virtual="false" hidden="false"></parameter>
	<parameter name="upravlenie" caption="Управление" type="string" multiple="false" domain="" format="" ag-id="0" ag-hash="-1602156091" description="" owner-id="0" virtual="false" hidden="false"></parameter>
	<parameter name="zapusk" caption="Запуск" type="string" multiple="false" domain="" format="" ag-id="0" ag-hash="-709176636" description="" owner-id="0" virtual="false" hidden="false"></parameter>
	<parameter name="podem" caption="Подъем" type="string" multiple="false" domain="" format="" ag-id="0" ag-hash="106840493" description="" owner-id="0" virtual="false" hidden="false"></parameter>
	<parameter name="tranets_plavsredstva" caption="Транец плавсредства" type="integer" multiple="false" domain="" format="" ag-id="0" ag-hash="1594059553" description="мм" owner-id="0" virtual="false" hidden="false"></parameter>
	<parameter name="svecha_zagiganiya_ngk" caption="Свеча зажигания (NGK)" type="string" multiple="false" domain="" format="" ag-id="0" ag-hash="-101941410" description="" owner-id="0" virtual="false" hidden="false"></parameter>
	<parameter name="toplivnyi_bak" caption="Топливный бак" type="integer" multiple="false" domain="" format="" ag-id="0" ag-hash="-576195929" description="л" owner-id="0" virtual="false" hidden="false"></parameter>
	<parameter name="vraschenie_vinta" caption="Вращение винта" type="string" multiple="false" domain="" format="" ag-id="0" ag-hash="1724986273" description="" owner-id="0" virtual="false" hidden="false"></parameter>
	<parameter name="reduktsiya" caption="Редукция" type="string" multiple="false" domain="" format="" ag-id="0" ag-hash="-971909173" description="" owner-id="0" virtual="false" hidden="false"></parameter>
	<parameter name="shtatnyi_vint" caption="Штатный винт" type="string" multiple="false" domain="" format="" ag-id="0" ag-hash="-676308340" description="" owner-id="0" virtual="false" hidden="false"></parameter>
	<parameter name="diapazon_vintov" caption="Диапазон винтов" type="string" multiple="false" domain="" format="" ag-id="0" ag-hash="-1377350221" description="" owner-id="0" virtual="false" hidden="false"></parameter>
	<parameter name="zadnii_hod" caption="Задний ход" type="string" multiple="false" domain="" format="" ag-id="0" ag-hash="-1594739249" description="" owner-id="0" virtual="false" hidden="false"></parameter>
	<parameter name="reduktor" caption="Редуктор" type="integer" multiple="false" domain="" format="" ag-id="0" ag-hash="-765256432" description="мл" owner-id="0" virtual="false" hidden="false"></parameter>
	<parameter name="karter" caption="Картер" type="integer" multiple="false" domain="" format="" ag-id="0" ag-hash="-1138555707" description="мл" owner-id="0" virtual="false" hidden="false"></parameter>
	<parameter name="ves" caption="Вес" type="integer" multiple="false" domain="" format="" ag-id="0" ag-hash="116644" description="кг" owner-id="0" virtual="false" hidden="false"></parameter>
	<parameter name="garantiya" caption="Гарантия" type="integer" multiple="false" domain="" format="" ag-id="0" ag-hash="1043041986" description="года" owner-id="0" virtual="false" hidden="false"></parameter>
	<parameter name="razmer_sm" caption="Размер, см" type="string" multiple="false" domain="" format="" ag-id="0" ag-hash="1481142986" description="" owner-id="0" virtual="false" hidden="false"></parameter>
	<parameter name="ves_brutto" caption="Вес брутто" type="integer" multiple="false" domain="" format="" ag-id="0" ag-hash="304704165" description="кг" owner-id="0" virtual="false" hidden="false"></parameter>
	<parameter name="obem" caption="Объем" type="double" multiple="false" domain="" format="" ag-id="0" ag-hash="3404219" description="м³" owner-id="0" virtual="false" hidden="false"></parameter>
	<parameter name="proizvoditel" caption="Производитель" type="string" multiple="false" domain="" format="" ag-id="0" ag-hash="235196415" description="" owner-id="0" virtual="false" hidden="false"></parameter>
	<parameter name="strana" caption="Страна" type="string" multiple="false" domain="" format="" ag-id="0" ag-hash="-891993597" description="" owner-id="0" virtual="false" hidden="false"></parameter>
</item>
<!--END_p382750-->

<!--START_p382773-->
<item name="p382773" caption="Моторы Suzuki 100...350 л.с." key="" virtual="false" user-def="true" description="" super="params *" ag-id="1789" ag-hash="2129512502">
	<parameter name="taktnost" caption="Тактность" type="integer" multiple="false" domain="" format="" ag-id="0" ag-hash="-630085256" description="-тактный" owner-id="0" virtual="false" hidden="false"></parameter>
	<parameter name="moschnost" caption="Мощность" type="integer" multiple="false" domain="" format="" ag-id="0" ag-hash="-1643161576" description="л.с." owner-id="0" virtual="false" hidden="false"></parameter>
	<parameter name="kol_vo_tsilindrov" caption="Кол-во цилиндров" type="integer" multiple="false" domain="" format="" ag-id="0" ag-hash="-1202498357" description="" owner-id="0" virtual="false" hidden="false"></parameter>
	<parameter name="obem_dvigatelya" caption="Объем двигателя" type="integer" multiple="false" domain="" format="" ag-id="0" ag-hash="1653502678" description="см³" owner-id="0" virtual="false" hidden="false"></parameter>
	<parameter name="tip_topliva" caption="Тип топлива" type="string" multiple="false" domain="" format="" ag-id="0" ag-hash="-799384551" description="" owner-id="0" virtual="false" hidden="false"></parameter>
	<parameter name="podacha_topliva" caption="Подача топлива" type="string" multiple="false" domain="" format="" ag-id="0" ag-hash="-1652185378" description="" owner-id="0" virtual="false" hidden="false"></parameter>
	<parameter name="sistema_smazki" caption="Система смазки" type="string" multiple="false" domain="" format="" ag-id="0" ag-hash="-2129155730" description="" owner-id="0" virtual="false" hidden="false"></parameter>
	<parameter name="diapazon_maks__oborotov" caption="Диапазон макс. оборотов" type="string" multiple="false" domain="" format="" ag-id="0" ag-hash="2134028465" description="" owner-id="0" virtual="false" hidden="false"></parameter>
	<parameter name="generator" caption="Генератор" type="string" multiple="false" domain="" format="" ag-id="0" ag-hash="286956243" description="" owner-id="0" virtual="false" hidden="false"></parameter>
	<parameter name="rekomenduemyi_akkumulyator" caption="Рекомендуемый аккумулятор" type="integer" multiple="false" domain="" format="" ag-id="0" ag-hash="378721238" description="Ah" owner-id="0" virtual="false" hidden="false"></parameter>
	<parameter name="upravlenie" caption="Управление" type="string" multiple="false" domain="" format="" ag-id="0" ag-hash="-1602156091" description="" owner-id="0" virtual="false" hidden="false"></parameter>
	<parameter name="zapusk" caption="Запуск" type="string" multiple="false" domain="" format="" ag-id="0" ag-hash="-709176636" description="" owner-id="0" virtual="false" hidden="false"></parameter>
	<parameter name="podem" caption="Подъем" type="string" multiple="false" domain="" format="" ag-id="0" ag-hash="106840493" description="" owner-id="0" virtual="false" hidden="false"></parameter>
	<parameter name="tranets_plavsredstva" caption="Транец плавсредства" type="integer" multiple="false" domain="" format="" ag-id="0" ag-hash="1594059553" description="мм" owner-id="0" virtual="false" hidden="false"></parameter>
	<parameter name="svecha_zagiganiya_ngk" caption="Свеча зажигания (NGK)" type="string" multiple="false" domain="" format="" ag-id="0" ag-hash="-101941410" description="" owner-id="0" virtual="false" hidden="false"></parameter>
	<parameter name="vraschenie_vinta" caption="Вращение винта" type="string" multiple="false" domain="" format="" ag-id="0" ag-hash="1724986273" description="" owner-id="0" virtual="false" hidden="false"></parameter>
	<parameter name="reduktsiya" caption="Редукция" type="string" multiple="false" domain="" format="" ag-id="0" ag-hash="-971909173" description="" owner-id="0" virtual="false" hidden="false"></parameter>
	<parameter name="shtatnyi_vint" caption="Штатный винт" type="string" multiple="false" domain="" format="" ag-id="0" ag-hash="-676308340" description="" owner-id="0" virtual="false" hidden="false"></parameter>
	<parameter name="diapazon_vintov" caption="Диапазон винтов" type="string" multiple="false" domain="" format="" ag-id="0" ag-hash="-1377350221" description="" owner-id="0" virtual="false" hidden="false"></parameter>
	<parameter name="zadnii_hod" caption="Задний ход" type="string" multiple="false" domain="" format="" ag-id="0" ag-hash="-1594739249" description="" owner-id="0" virtual="false" hidden="false"></parameter>
	<parameter name="reduktor" caption="Редуктор" type="integer" multiple="false" domain="" format="" ag-id="0" ag-hash="-765256432" description="мл" owner-id="0" virtual="false" hidden="false"></parameter>
	<parameter name="karter" caption="Картер" type="integer" multiple="false" domain="" format="" ag-id="0" ag-hash="-1138555707" description="мл" owner-id="0" virtual="false" hidden="false"></parameter>
	<parameter name="ves" caption="Вес" type="integer" multiple="false" domain="" format="" ag-id="0" ag-hash="116644" description="кг" owner-id="0" virtual="false" hidden="false"></parameter>
	<parameter name="garantiya" caption="Гарантия" type="integer" multiple="false" domain="" format="" ag-id="0" ag-hash="1043041986" description="года" owner-id="0" virtual="false" hidden="false"></parameter>
	<parameter name="razmer_sm" caption="Размер, см" type="string" multiple="false" domain="" format="" ag-id="0" ag-hash="1481142986" description="" owner-id="0" virtual="false" hidden="false"></parameter>
	<parameter name="obem" caption="Объем" type="double" multiple="false" domain="" format="" ag-id="0" ag-hash="3404219" description="м³" owner-id="0" virtual="false" hidden="false"></parameter>
	<parameter name="proizvoditel" caption="Производитель" type="string" multiple="false" domain="" format="" ag-id="0" ag-hash="235196415" description="" owner-id="0" virtual="false" hidden="false"></parameter>
	<parameter name="strana" caption="Страна" type="string" multiple="false" domain="" format="" ag-id="0" ag-hash="-891993597" description="" owner-id="0" virtual="false" hidden="false"></parameter>
	<parameter name="ves_brutto" caption="Вес брутто" type="integer" multiple="false" domain="" format="" ag-id="0" ag-hash="304704165" description="кг" owner-id="0" virtual="false" hidden="false"></parameter>
</item>
<!--END_p382773-->

<!--START_p382830-->
<item name="p382830" caption="2-тактные моторы" key="" virtual="false" user-def="true" description="" super="params *" ag-id="1790" ag-hash="2129513336">
	<parameter name="taktnost" caption="Тактность" type="integer" multiple="false" domain="" format="" ag-id="0" ag-hash="-630085256" description="-тактный" owner-id="0" virtual="false" hidden="false"></parameter>
	<parameter name="moschnost" caption="Мощность" type="double" multiple="false" domain="" format="" ag-id="0" ag-hash="-1643161576" description="л.с." owner-id="0" virtual="false" hidden="false"></parameter>
	<parameter name="kol_vo_tsilindrov" caption="Кол-во цилиндров" type="integer" multiple="false" domain="" format="" ag-id="0" ag-hash="-1202498357" description="" owner-id="0" virtual="false" hidden="false"></parameter>
	<parameter name="obem_dvigatelya" caption="Объем двигателя" type="integer" multiple="false" domain="" format="" ag-id="0" ag-hash="1653502678" description="см³" owner-id="0" virtual="false" hidden="false"></parameter>
	<parameter name="tip_topliva" caption="Тип топлива" type="string" multiple="false" domain="" format="" ag-id="0" ag-hash="-799384551" description="" owner-id="0" virtual="false" hidden="false"></parameter>
	<parameter name="podacha_topliva" caption="Подача топлива" type="string" multiple="false" domain="" format="" ag-id="0" ag-hash="-1652185378" description="" owner-id="0" virtual="false" hidden="false"></parameter>
	<parameter name="sistema_smazki" caption="Система смазки" type="string" multiple="false" domain="" format="" ag-id="0" ag-hash="-2129155730" description="" owner-id="0" virtual="false" hidden="false"></parameter>
	<parameter name="diapazon_maks__oborotov" caption="Диапазон макс. оборотов" type="string" multiple="false" domain="" format="" ag-id="0" ag-hash="2134028465" description="" owner-id="0" virtual="false" hidden="false"></parameter>
	<parameter name="generator" caption="Генератор" type="string" multiple="false" domain="" format="" ag-id="0" ag-hash="286956243" description="" owner-id="0" virtual="false" hidden="false"></parameter>
	<parameter name="rekomenduemyi_akkumulyator" caption="Рекомендуемый аккумулятор" type="string" multiple="false" domain="" format="" ag-id="0" ag-hash="378721238" description="Ah" owner-id="0" virtual="false" hidden="false"></parameter>
	<parameter name="upravlenie" caption="Управление" type="string" multiple="false" domain="" format="" ag-id="0" ag-hash="-1602156091" description="" owner-id="0" virtual="false" hidden="false"></parameter>
	<parameter name="zapusk" caption="Запуск" type="string" multiple="false" domain="" format="" ag-id="0" ag-hash="-709176636" description="" owner-id="0" virtual="false" hidden="false"></parameter>
	<parameter name="podem" caption="Подъем" type="string" multiple="false" domain="" format="" ag-id="0" ag-hash="106840493" description="" owner-id="0" virtual="false" hidden="false"></parameter>
	<parameter name="tranets_plavsredstva" caption="Транец плавсредства" type="integer" multiple="false" domain="" format="" ag-id="0" ag-hash="1594059553" description="мм" owner-id="0" virtual="false" hidden="false"></parameter>
	<parameter name="svecha_zagiganiya_ngk" caption="Свеча зажигания (NGK)" type="string" multiple="false" domain="" format="" ag-id="0" ag-hash="-101941410" description="" owner-id="0" virtual="false" hidden="false"></parameter>
	<parameter name="toplivnyi_bak" caption="Топливный бак" type="integer" multiple="false" domain="" format="" ag-id="0" ag-hash="-576195929" description="л" owner-id="0" virtual="false" hidden="false"></parameter>
	<parameter name="vraschenie_vinta" caption="Вращение винта" type="string" multiple="false" domain="" format="" ag-id="0" ag-hash="1724986273" description="" owner-id="0" virtual="false" hidden="false"></parameter>
	<parameter name="reduktsiya" caption="Редукция" type="string" multiple="false" domain="" format="" ag-id="0" ag-hash="-971909173" description="" owner-id="0" virtual="false" hidden="false"></parameter>
	<parameter name="shtatnyi_vint" caption="Штатный винт" type="string" multiple="false" domain="" format="" ag-id="0" ag-hash="-676308340" description="" owner-id="0" virtual="false" hidden="false"></parameter>
	<parameter name="diapazon_vintov" caption="Диапазон винтов" type="string" multiple="false" domain="" format="" ag-id="0" ag-hash="-1377350221" description="" owner-id="0" virtual="false" hidden="false"></parameter>
	<parameter name="zadnii_hod" caption="Задний ход" type="string" multiple="false" domain="" format="" ag-id="0" ag-hash="-1594739249" description="" owner-id="0" virtual="false" hidden="false"></parameter>
	<parameter name="reduktor" caption="Редуктор" type="integer" multiple="false" domain="" format="" ag-id="0" ag-hash="-765256432" description="мл" owner-id="0" virtual="false" hidden="false"></parameter>
	<parameter name="ves" caption="Вес" type="double" multiple="false" domain="" format="" ag-id="0" ag-hash="116644" description="кг" owner-id="0" virtual="false" hidden="false"></parameter>
	<parameter name="garantiya" caption="Гарантия" type="integer" multiple="false" domain="" format="" ag-id="0" ag-hash="1043041986" description="года" owner-id="0" virtual="false" hidden="false"></parameter>
	<parameter name="razmer_sm" caption="Размер, см" type="string" multiple="false" domain="" format="" ag-id="0" ag-hash="1481142986" description="" owner-id="0" virtual="false" hidden="false"></parameter>
	<parameter name="ves_brutto" caption="Вес брутто" type="integer" multiple="false" domain="" format="" ag-id="0" ag-hash="304704165" description="кг" owner-id="0" virtual="false" hidden="false"></parameter>
	<parameter name="obem" caption="Объем" type="double" multiple="false" domain="" format="" ag-id="0" ag-hash="3404219" description="м³" owner-id="0" virtual="false" hidden="false"></parameter>
	<parameter name="proizvoditel" caption="Производитель" type="string" multiple="false" domain="" format="" ag-id="0" ag-hash="235196415" description="" owner-id="0" virtual="false" hidden="false"></parameter>
	<parameter name="strana" caption="Страна" type="string" multiple="false" domain="" format="" ag-id="0" ag-hash="-891993597" description="" owner-id="0" virtual="false" hidden="false"></parameter>
</item>
<!--END_p382830-->

<!--START_p386338-->
<item name="p386338" caption="Шторы на ленте" key="" virtual="false" user-def="true" description="" super="params *" ag-id="1816" ag-hash="2129627703">
	<parameter name="kolichestvo_ryadov_petel" caption="Количество рядов петель" type="integer" multiple="false" domain="" format="" ag-id="0" ag-hash="-973409698" description="" owner-id="0" virtual="false" hidden="false"></parameter>
	<parameter name="kolichestvo_styagivayuschih_shnurov" caption="Количество стягивающих шнуров" type="integer" multiple="false" domain="" format="" ag-id="0" ag-hash="-1160615267" description="" owner-id="0" virtual="false" hidden="false"></parameter>
	<parameter name="koeffitsient_sborki" caption="Коэффициент сборки" type="string" multiple="false" domain="" format="" ag-id="0" ag-hash="-2086101786" description="" owner-id="0" virtual="false" hidden="false"></parameter>
	<parameter name="rapport" caption="Раппорт" type="integer" multiple="false" domain="" format="" ag-id="0" ag-hash="980113442" description="" owner-id="0" virtual="false" hidden="false"></parameter>
	<parameter name="risunok" caption="Рисунок" type="string" multiple="false" domain="" format="" ag-id="0" ag-hash="1212065105" description="" owner-id="0" virtual="false" hidden="false"></parameter>
	<parameter name="tip_podhvata" caption="Тип подхвата" type="string" multiple="false" domain="" format="" ag-id="0" ag-hash="-2034267457" description="" owner-id="0" virtual="false" hidden="false"></parameter>
	<parameter name="tip_skladki" caption="Тип складки" type="string" multiple="false" domain="" format="" ag-id="0" ag-hash="-1805431759" description="" owner-id="0" virtual="false" hidden="false"></parameter>
	<parameter name="tsvet" caption="Цвет" type="string" multiple="false" domain="" format="" ag-id="0" ag-hash="110671046" description="" owner-id="0" virtual="false" hidden="false"></parameter>
	<parameter name="ves" caption="Вес" type="double" multiple="false" domain="" format="" ag-id="0" ag-hash="116644" description="" owner-id="0" virtual="false" hidden="false"></parameter>
	<parameter name="vysota" caption="Высота" type="integer" multiple="false" domain="" format="" ag-id="0" ag-hash="-801445108" description="" owner-id="0" virtual="false" hidden="false"></parameter>
	<parameter name="dlina_karniza" caption="Длина карниза" type="string" multiple="false" domain="" format="" ag-id="0" ag-hash="-164308205" description="" owner-id="0" virtual="false" hidden="false"></parameter>
	<parameter name="dlina_podhvata" caption="Длина подхвата" type="integer" multiple="false" domain="" format="" ag-id="0" ag-hash="-1540305626" description="" owner-id="0" virtual="false" hidden="false"></parameter>
	<parameter name="shirina" caption="Ширина" type="integer" multiple="false" domain="" format="" ag-id="0" ag-hash="2061610206" description="" owner-id="0" virtual="false" hidden="false"></parameter>
	<parameter name="kollektsiya" caption="Коллекция" type="string" multiple="false" domain="" format="" ag-id="0" ag-hash="592508680" description="" owner-id="0" virtual="false" hidden="false"></parameter>
	<parameter name="model" caption="Модель" type="string" multiple="false" domain="" format="" ag-id="0" ag-hash="104069929" description="" owner-id="0" virtual="false" hidden="false"></parameter>
	<parameter name="strana_proizvodstva" caption="Страна производства" type="string" multiple="false" domain="" format="" ag-id="0" ag-hash="-1685577099" description="" owner-id="0" virtual="false" hidden="false"></parameter>
	<parameter name="instruktsiya" caption="Инструкция" type="integer" multiple="false" domain="" format="" ag-id="0" ag-hash="986702096" description="" owner-id="0" virtual="false" hidden="false"></parameter>
	<parameter name="paket_upakovochnyi" caption="Пакет упаковочный" type="integer" multiple="false" domain="" format="" ag-id="0" ag-hash="-2024521780" description="" owner-id="0" virtual="false" hidden="false"></parameter>
	<parameter name="podhvat_dlya_shtor" caption="Подхват для штор" type="integer" multiple="false" domain="" format="" ag-id="0" ag-hash="-1749985332" description="" owner-id="0" virtual="false" hidden="false"></parameter>
	<parameter name="fiksator_shnura" caption="Фиксатор шнура" type="integer" multiple="false" domain="" format="" ag-id="0" ag-hash="-1435450679" description="" owner-id="0" virtual="false" hidden="false"></parameter>
	<parameter name="shtornoe_izdelie" caption="Шторное изделие" type="integer" multiple="false" domain="" format="" ag-id="0" ag-hash="-2146485959" description="" owner-id="0" virtual="false" hidden="false"></parameter>
	<parameter name="bokovye_storony" caption="Боковые стороны" type="string" multiple="false" domain="" format="" ag-id="0" ag-hash="257182632" description="" owner-id="0" virtual="false" hidden="false"></parameter>
	<parameter name="verhnyaya_storona" caption="Верхняя сторона" type="string" multiple="false" domain="" format="" ag-id="0" ag-hash="1031302424" description="" owner-id="0" virtual="false" hidden="false"></parameter>
	<parameter name="vid_tkani" caption="Вид ткани" type="string" multiple="false" domain="" format="" ag-id="0" ag-hash="1166466647" description="" owner-id="0" virtual="false" hidden="false"></parameter>
	<parameter name="material" caption="Материал" type="string" multiple="false" domain="" format="" ag-id="0" ag-hash="299066663" description="" owner-id="0" virtual="false" hidden="false"></parameter>
	<parameter name="nignyaya_storona" caption="Нижняя сторона" type="string" multiple="false" domain="" format="" ag-id="0" ag-hash="-222797935" description="" owner-id="0" virtual="false" hidden="false"></parameter>
	<parameter name="osobye_svoistva" caption="Особые свойства" type="string" multiple="false" domain="" format="" ag-id="0" ag-hash="1606100613" description="" owner-id="0" virtual="false" hidden="false"></parameter>
	<parameter name="sostav" caption="Состав" type="double" multiple="false" domain="" format="" ag-id="0" ag-hash="-896563534" description="" owner-id="0" virtual="false" hidden="false"></parameter>
	<parameter name="kategoriya" caption="Категория" type="string" multiple="false" domain="" format="" ag-id="0" ag-hash="-275590802" description="" owner-id="0" virtual="false" hidden="false"></parameter>
	<parameter name="tip_karniza" caption="Тип карниза" type="string" multiple="false" domain="" format="" ag-id="0" ag-hash="-595884454" description="" owner-id="0" virtual="false" hidden="false"></parameter>
	<parameter name="tip_krepleniya" caption="Тип крепления" type="string" multiple="false" domain="" format="" ag-id="0" ag-hash="-895594510" description="" owner-id="0" virtual="false" hidden="false"></parameter>
</item>
<!--END_p386338-->

<!--START_paa-->
<item name="paa" caption="Шторы на ленте" key="" virtual="false" user-def="true" description="" super="params *" ag-id="1819" ag-hash="110736">
	<parameter name="kolichestvo_ryadov_petel" caption="Количество рядов петель" type="integer" multiple="false" domain="" format="" ag-id="0" ag-hash="-973409698" description="" owner-id="0" virtual="false" hidden="false"></parameter>
	<parameter name="kolichestvo_styagivayuschih_shnurov" caption="Количество стягивающих шнуров" type="integer" multiple="false" domain="" format="" ag-id="0" ag-hash="-1160615267" description="" owner-id="0" virtual="false" hidden="false"></parameter>
	<parameter name="koeffitsient_sborki" caption="Коэффициент сборки" type="string" multiple="false" domain="" format="" ag-id="0" ag-hash="-2086101786" description="" owner-id="0" virtual="false" hidden="false"></parameter>
	<parameter name="rapport" caption="Раппорт" type="integer" multiple="false" domain="" format="" ag-id="0" ag-hash="980113442" description="" owner-id="0" virtual="false" hidden="false"></parameter>
	<parameter name="risunok" caption="Рисунок" type="string" multiple="false" domain="" format="" ag-id="0" ag-hash="1212065105" description="" owner-id="0" virtual="false" hidden="false"></parameter>
	<parameter name="tip_podhvata" caption="Тип подхвата" type="string" multiple="false" domain="" format="" ag-id="0" ag-hash="-2034267457" description="" owner-id="0" virtual="false" hidden="false"></parameter>
	<parameter name="tip_skladki" caption="Тип складки" type="string" multiple="false" domain="" format="" ag-id="0" ag-hash="-1805431759" description="" owner-id="0" virtual="false" hidden="false"></parameter>
	<parameter name="tsvet" caption="Цвет" type="string" multiple="false" domain="" format="" ag-id="0" ag-hash="110671046" description="" owner-id="0" virtual="false" hidden="false"></parameter>
	<parameter name="ves" caption="Вес" type="double" multiple="false" domain="" format="" ag-id="0" ag-hash="116644" description="" owner-id="0" virtual="false" hidden="false"></parameter>
	<parameter name="vysota" caption="Высота" type="integer" multiple="false" domain="" format="" ag-id="0" ag-hash="-801445108" description="" owner-id="0" virtual="false" hidden="false"></parameter>
	<parameter name="dlina_karniza" caption="Длина карниза" type="string" multiple="false" domain="" format="" ag-id="0" ag-hash="-164308205" description="" owner-id="0" virtual="false" hidden="false"></parameter>
	<parameter name="dlina_podhvata" caption="Длина подхвата" type="integer" multiple="false" domain="" format="" ag-id="0" ag-hash="-1540305626" description="" owner-id="0" virtual="false" hidden="false"></parameter>
	<parameter name="shirina" caption="Ширина" type="integer" multiple="false" domain="" format="" ag-id="0" ag-hash="2061610206" description="" owner-id="0" virtual="false" hidden="false"></parameter>
	<parameter name="kollektsiya" caption="Коллекция" type="string" multiple="false" domain="" format="" ag-id="0" ag-hash="592508680" description="" owner-id="0" virtual="false" hidden="false"></parameter>
	<parameter name="model" caption="Модель" type="string" multiple="false" domain="" format="" ag-id="0" ag-hash="104069929" description="" owner-id="0" virtual="false" hidden="false"></parameter>
	<parameter name="strana_proizvodstva" caption="Страна производства" type="string" multiple="false" domain="" format="" ag-id="0" ag-hash="-1685577099" description="" owner-id="0" virtual="false" hidden="false"></parameter>
	<parameter name="instruktsiya" caption="Инструкция" type="integer" multiple="false" domain="" format="" ag-id="0" ag-hash="986702096" description="" owner-id="0" virtual="false" hidden="false"></parameter>
	<parameter name="paket_upakovochnyi" caption="Пакет упаковочный" type="integer" multiple="false" domain="" format="" ag-id="0" ag-hash="-2024521780" description="" owner-id="0" virtual="false" hidden="false"></parameter>
	<parameter name="podhvat_dlya_shtor" caption="Подхват для штор" type="integer" multiple="false" domain="" format="" ag-id="0" ag-hash="-1749985332" description="" owner-id="0" virtual="false" hidden="false"></parameter>
	<parameter name="fiksator_shnura" caption="Фиксатор шнура" type="integer" multiple="false" domain="" format="" ag-id="0" ag-hash="-1435450679" description="" owner-id="0" virtual="false" hidden="false"></parameter>
	<parameter name="shtornoe_izdelie" caption="Шторное изделие" type="integer" multiple="false" domain="" format="" ag-id="0" ag-hash="-2146485959" description="" owner-id="0" virtual="false" hidden="false"></parameter>
	<parameter name="bokovye_storony" caption="Боковые стороны" type="string" multiple="false" domain="" format="" ag-id="0" ag-hash="257182632" description="" owner-id="0" virtual="false" hidden="false"></parameter>
	<parameter name="verhnyaya_storona" caption="Верхняя сторона" type="string" multiple="false" domain="" format="" ag-id="0" ag-hash="1031302424" description="" owner-id="0" virtual="false" hidden="false"></parameter>
	<parameter name="vid_tkani" caption="Вид ткани" type="string" multiple="false" domain="" format="" ag-id="0" ag-hash="1166466647" description="" owner-id="0" virtual="false" hidden="false"></parameter>
	<parameter name="material" caption="Материал" type="string" multiple="false" domain="" format="" ag-id="0" ag-hash="299066663" description="" owner-id="0" virtual="false" hidden="false"></parameter>
	<parameter name="nignyaya_storona" caption="Нижняя сторона" type="string" multiple="false" domain="" format="" ag-id="0" ag-hash="-222797935" description="" owner-id="0" virtual="false" hidden="false"></parameter>
	<parameter name="osobye_svoistva" caption="Особые свойства" type="string" multiple="false" domain="" format="" ag-id="0" ag-hash="1606100613" description="" owner-id="0" virtual="false" hidden="false"></parameter>
	<parameter name="kategoriya" caption="Категория" type="string" multiple="false" domain="" format="" ag-id="0" ag-hash="-275590802" description="" owner-id="0" virtual="false" hidden="false"></parameter>
	<parameter name="tip_karniza" caption="Тип карниза" type="string" multiple="false" domain="" format="" ag-id="0" ag-hash="-595884454" description="" owner-id="0" virtual="false" hidden="false"></parameter>
	<parameter name="tip_krepleniya" caption="Тип крепления" type="string" multiple="false" domain="" format="" ag-id="0" ag-hash="-895594510" description="" owner-id="0" virtual="false" hidden="false"></parameter>
</item>
<!--END_paa-->

<!--START_pt1-->
<item name="pt1" caption="Ткани тюлевые" key="" virtual="false" user-def="true" description="" super="params *" ag-id="1820" ag-hash="111277">
	<parameter name="vid" caption="Вид" type="string" multiple="false" domain="" format="" ag-id="0" ag-hash="116753" description="" owner-id="0" virtual="false" hidden="false"></parameter>
	<parameter name="kategoriya" caption="Категория" type="string" multiple="false" domain="" format="" ag-id="0" ag-hash="-275590802" description="" owner-id="0" virtual="false" hidden="false"></parameter>
	<parameter name="kollektsiya" caption="Коллекция" type="string" multiple="false" domain="" format="" ag-id="0" ag-hash="592508680" description="" owner-id="0" virtual="false" hidden="false"></parameter>
	<parameter name="strana" caption="Страна" type="string" multiple="false" domain="" format="" ag-id="0" ag-hash="-891993597" description="" owner-id="0" virtual="false" hidden="false"></parameter>
	<parameter name="brend" caption="Бренд" type="double" multiple="false" domain="" format="" ag-id="0" ag-hash="94001803" description="" owner-id="0" virtual="false" hidden="false"></parameter>
	<parameter name="artikul" caption="Артикул" type="integer" multiple="false" domain="" format="" ag-id="0" ag-hash="-732369892" description="" owner-id="0" virtual="false" hidden="false"></parameter>
	<parameter name="tsvet" caption="Цвет" type="string" multiple="false" domain="" format="" ag-id="0" ag-hash="110671046" description="" owner-id="0" virtual="false" hidden="false"></parameter>
	<parameter name="tsvetovoi_ottenok" caption="Цветовой оттенок" type="string" multiple="false" domain="" format="" ag-id="0" ag-hash="2026120060" description="" owner-id="0" virtual="false" hidden="false"></parameter>
	<parameter name="parametry_tsveta" caption="Параметры цвета" type="string" multiple="false" domain="" format="" ag-id="0" ag-hash="-195540265" description="" owner-id="0" virtual="false" hidden="false"></parameter>
	<parameter name="shirina" caption="Ширина" type="integer" multiple="false" domain="" format="" ag-id="0" ag-hash="2061610206" description="см" owner-id="0" virtual="false" hidden="false"></parameter>
	<parameter name="sostav" caption="Состав" type="string" multiple="false" domain="" format="" ag-id="0" ag-hash="-896563534" description="" owner-id="0" virtual="false" hidden="false"></parameter>
	<parameter name="osobye_svoistva" caption="Особые свойства" type="double" multiple="false" domain="" format="" ag-id="0" ag-hash="1606100613" description="" owner-id="0" virtual="false" hidden="false"></parameter>
	<parameter name="svetopronitsaemost" caption="Светопроницаемость" type="integer" multiple="false" domain="" format="" ag-id="0" ag-hash="-1091719983" description="%" owner-id="0" virtual="false" hidden="false"></parameter>
	<parameter name="prozrachnost" caption="Прозрачность" type="string" multiple="false" domain="" format="" ag-id="0" ag-hash="1013208867" description="" owner-id="0" virtual="false" hidden="false"></parameter>
	<parameter name="plotnost" caption="Плотность" type="double" multiple="false" domain="" format="" ag-id="0" ag-hash="-2019236797" description="гр/м²" owner-id="0" virtual="false" hidden="false"></parameter>
	<parameter name="iznosostoikost" caption="Износостойкость" type="double" multiple="false" domain="" format="" ag-id="0" ag-hash="-1737542706" description="" owner-id="0" virtual="false" hidden="false"></parameter>
	<parameter name="risunok" caption="Рисунок" type="string" multiple="false" domain="" format="" ag-id="0" ag-hash="1212065105" description="" owner-id="0" virtual="false" hidden="false"></parameter>
	<parameter name="stil" caption="Стиль" type="string" multiple="false" domain="" format="" ag-id="0" ag-hash="3540804" description="" owner-id="0" virtual="false" hidden="false"></parameter>
	<parameter name="napravlenie_risunka" caption="Направление рисунка" type="double" multiple="false" domain="" format="" ag-id="0" ag-hash="-391113005" description="" owner-id="0" virtual="false" hidden="false"></parameter>
	<parameter name="rapport_gorizontalnyi" caption="Раппорт горизонтальный" type="double" multiple="false" domain="" format="" ag-id="0" ag-hash="1451310460" description="" owner-id="0" virtual="false" hidden="false"></parameter>
	<parameter name="rapport_vertikalnyi" caption="Раппорт вертикальный" type="double" multiple="false" domain="" format="" ag-id="0" ag-hash="233759011" description="" owner-id="0" virtual="false" hidden="false"></parameter>
	<parameter name="bordyur" caption="Бордюр" type="double" multiple="false" domain="" format="" ag-id="0" ag-hash="67263799" description="" owner-id="0" virtual="false" hidden="false"></parameter>
	<parameter name="vysota_bordyura" caption="Высота бордюра" type="double" multiple="false" domain="" format="" ag-id="0" ag-hash="821902813" description="" owner-id="0" virtual="false" hidden="false"></parameter>
	<parameter name="rapport_bordyura" caption="Раппорт бордюра" type="double" multiple="false" domain="" format="" ag-id="0" ag-hash="-2142819961" description="" owner-id="0" virtual="false" hidden="false"></parameter>
	<parameter name="utyagelitel" caption="Утяжелитель" type="string" multiple="false" domain="" format="" ag-id="0" ag-hash="697704345" description="" owner-id="0" virtual="false" hidden="false"></parameter>
	<parameter name="stirka" caption="Стирка" type="string" multiple="false" domain="" format="" ag-id="0" ag-hash="-892245472" description="" owner-id="0" virtual="false" hidden="false"></parameter>
	<parameter name="otgim" caption="Отжим" type="string" multiple="false" domain="" format="" ag-id="0" ag-hash="106068934" description="" owner-id="0" virtual="false" hidden="false"></parameter>
	<parameter name="sushka" caption="Сушка" type="string" multiple="false" domain="" format="" ag-id="0" ag-hash="-891033651" description="" owner-id="0" virtual="false" hidden="false"></parameter>
	<parameter name="glagka" caption="Глажка" type="string" multiple="false" domain="" format="" ag-id="0" ag-hash="-1243432351" description="" owner-id="0" virtual="false" hidden="false"></parameter>
	<parameter name="otbelivanie" caption="Отбеливание" type="string" multiple="false" domain="" format="" ag-id="0" ag-hash="158623290" description="" owner-id="0" virtual="false" hidden="false"></parameter>
	<parameter name="himchistka" caption="Химчистка" type="string" multiple="false" domain="" format="" ag-id="0" ag-hash="1967533327" description="" owner-id="0" virtual="false" hidden="false"></parameter>
	<parameter name="akvachistka" caption="Аквачистка" type="double" multiple="false" domain="" format="" ag-id="0" ag-hash="1706411046" description="" owner-id="0" virtual="false" hidden="false"></parameter>
</item>
<!--END_pt1-->

<!--START_pt2-->
<item name="pt2" caption="Ткани портьерные" key="" virtual="false" user-def="true" description="" super="params *" ag-id="1821" ag-hash="111278">
	<parameter name="vid" caption="Вид" type="string" multiple="false" domain="" format="" ag-id="0" ag-hash="116753" description="" owner-id="0" virtual="false" hidden="false"></parameter>
	<parameter name="kategoriya" caption="Категория" type="string" multiple="false" domain="" format="" ag-id="0" ag-hash="-275590802" description="" owner-id="0" virtual="false" hidden="false"></parameter>
	<parameter name="kollektsiya" caption="Коллекция" type="string" multiple="false" domain="" format="" ag-id="0" ag-hash="592508680" description="" owner-id="0" virtual="false" hidden="false"></parameter>
	<parameter name="strana" caption="Страна" type="string" multiple="false" domain="" format="" ag-id="0" ag-hash="-891993597" description="" owner-id="0" virtual="false" hidden="false"></parameter>
	<parameter name="brend" caption="Бренд" type="double" multiple="false" domain="" format="" ag-id="0" ag-hash="94001803" description="" owner-id="0" virtual="false" hidden="false"></parameter>
	<parameter name="artikul" caption="Артикул" type="integer" multiple="false" domain="" format="" ag-id="0" ag-hash="-732369892" description="" owner-id="0" virtual="false" hidden="false"></parameter>
	<parameter name="tsvet" caption="Цвет" type="string" multiple="false" domain="" format="" ag-id="0" ag-hash="110671046" description="" owner-id="0" virtual="false" hidden="false"></parameter>
	<parameter name="tsvetovoi_ottenok" caption="Цветовой оттенок" type="string" multiple="false" domain="" format="" ag-id="0" ag-hash="2026120060" description="" owner-id="0" virtual="false" hidden="false"></parameter>
	<parameter name="parametry_tsveta" caption="Параметры цвета" type="string" multiple="false" domain="" format="" ag-id="0" ag-hash="-195540265" description="" owner-id="0" virtual="false" hidden="false"></parameter>
	<parameter name="shirina" caption="Ширина" type="integer" multiple="false" domain="" format="" ag-id="0" ag-hash="2061610206" description="см" owner-id="0" virtual="false" hidden="false"></parameter>
	<parameter name="sostav" caption="Состав" type="string" multiple="false" domain="" format="" ag-id="0" ag-hash="-896563534" description="" owner-id="0" virtual="false" hidden="false"></parameter>
	<parameter name="osobye_svoistva" caption="Особые свойства" type="string" multiple="false" domain="" format="" ag-id="0" ag-hash="1606100613" description="" owner-id="0" virtual="false" hidden="false"></parameter>
	<parameter name="svetopronitsaemost" caption="Светопроницаемость" type="double" multiple="false" domain="" format="" ag-id="0" ag-hash="-1091719983" description="%" owner-id="0" virtual="false" hidden="false"></parameter>
	<parameter name="prozrachnost" caption="Прозрачность" type="double" multiple="false" domain="" format="" ag-id="0" ag-hash="1013208867" description="" owner-id="0" virtual="false" hidden="false"></parameter>
	<parameter name="plotnost" caption="Плотность" type="double" multiple="false" domain="" format="" ag-id="0" ag-hash="-2019236797" description="гр/м²" owner-id="0" virtual="false" hidden="false"></parameter>
	<parameter name="iznosostoikost" caption="Износостойкость" type="double" multiple="false" domain="" format="" ag-id="0" ag-hash="-1737542706" description="" owner-id="0" virtual="false" hidden="false"></parameter>
	<parameter name="risunok" caption="Рисунок" type="string" multiple="false" domain="" format="" ag-id="0" ag-hash="1212065105" description="" owner-id="0" virtual="false" hidden="false"></parameter>
	<parameter name="stil" caption="Стиль" type="string" multiple="false" domain="" format="" ag-id="0" ag-hash="3540804" description="" owner-id="0" virtual="false" hidden="false"></parameter>
	<parameter name="napravlenie_risunka" caption="Направление рисунка" type="double" multiple="false" domain="" format="" ag-id="0" ag-hash="-391113005" description="" owner-id="0" virtual="false" hidden="false"></parameter>
	<parameter name="rapport_gorizontalnyi" caption="Раппорт горизонтальный" type="double" multiple="false" domain="" format="" ag-id="0" ag-hash="1451310460" description="" owner-id="0" virtual="false" hidden="false"></parameter>
	<parameter name="rapport_vertikalnyi" caption="Раппорт вертикальный" type="double" multiple="false" domain="" format="" ag-id="0" ag-hash="233759011" description="" owner-id="0" virtual="false" hidden="false"></parameter>
	<parameter name="bordyur" caption="Бордюр" type="double" multiple="false" domain="" format="" ag-id="0" ag-hash="67263799" description="" owner-id="0" virtual="false" hidden="false"></parameter>
	<parameter name="vysota_bordyura" caption="Высота бордюра" type="double" multiple="false" domain="" format="" ag-id="0" ag-hash="821902813" description="" owner-id="0" virtual="false" hidden="false"></parameter>
	<parameter name="rapport_bordyura" caption="Раппорт бордюра" type="double" multiple="false" domain="" format="" ag-id="0" ag-hash="-2142819961" description="" owner-id="0" virtual="false" hidden="false"></parameter>
	<parameter name="utyagelitel" caption="Утяжелитель" type="double" multiple="false" domain="" format="" ag-id="0" ag-hash="697704345" description="" owner-id="0" virtual="false" hidden="false"></parameter>
	<parameter name="stirka" caption="Стирка" type="string" multiple="false" domain="" format="" ag-id="0" ag-hash="-892245472" description="" owner-id="0" virtual="false" hidden="false"></parameter>
	<parameter name="otgim" caption="Отжим" type="string" multiple="false" domain="" format="" ag-id="0" ag-hash="106068934" description="" owner-id="0" virtual="false" hidden="false"></parameter>
	<parameter name="sushka" caption="Сушка" type="string" multiple="false" domain="" format="" ag-id="0" ag-hash="-891033651" description="" owner-id="0" virtual="false" hidden="false"></parameter>
	<parameter name="glagka" caption="Глажка" type="string" multiple="false" domain="" format="" ag-id="0" ag-hash="-1243432351" description="" owner-id="0" virtual="false" hidden="false"></parameter>
	<parameter name="otbelivanie" caption="Отбеливание" type="string" multiple="false" domain="" format="" ag-id="0" ag-hash="158623290" description="" owner-id="0" virtual="false" hidden="false"></parameter>
	<parameter name="himchistka" caption="Химчистка" type="string" multiple="false" domain="" format="" ag-id="0" ag-hash="1967533327" description="" owner-id="0" virtual="false" hidden="false"></parameter>
	<parameter name="akvachistka" caption="Аквачистка" type="double" multiple="false" domain="" format="" ag-id="0" ag-hash="1706411046" description="" owner-id="0" virtual="false" hidden="false"></parameter>
</item>
<!--END_pt2-->

<!--START_pt3-->
<item name="pt3" caption="Ткани блэкаут" key="" virtual="false" user-def="true" description="" super="params *" ag-id="1822" ag-hash="111279">
	<parameter name="vid" caption="Вид" type="string" multiple="false" domain="" format="" ag-id="0" ag-hash="116753" description="" owner-id="0" virtual="false" hidden="false"></parameter>
	<parameter name="kategoriya" caption="Категория" type="string" multiple="false" domain="" format="" ag-id="0" ag-hash="-275590802" description="" owner-id="0" virtual="false" hidden="false"></parameter>
	<parameter name="kollektsiya" caption="Коллекция" type="string" multiple="false" domain="" format="" ag-id="0" ag-hash="592508680" description="" owner-id="0" virtual="false" hidden="false"></parameter>
	<parameter name="strana" caption="Страна" type="string" multiple="false" domain="" format="" ag-id="0" ag-hash="-891993597" description="" owner-id="0" virtual="false" hidden="false"></parameter>
	<parameter name="brend" caption="Бренд" type="double" multiple="false" domain="" format="" ag-id="0" ag-hash="94001803" description="" owner-id="0" virtual="false" hidden="false"></parameter>
	<parameter name="artikul" caption="Артикул" type="integer" multiple="false" domain="" format="" ag-id="0" ag-hash="-732369892" description="" owner-id="0" virtual="false" hidden="false"></parameter>
	<parameter name="tsvet" caption="Цвет" type="string" multiple="false" domain="" format="" ag-id="0" ag-hash="110671046" description="" owner-id="0" virtual="false" hidden="false"></parameter>
	<parameter name="tsvetovoi_ottenok" caption="Цветовой оттенок" type="string" multiple="false" domain="" format="" ag-id="0" ag-hash="2026120060" description="" owner-id="0" virtual="false" hidden="false"></parameter>
	<parameter name="parametry_tsveta" caption="Параметры цвета" type="string" multiple="false" domain="" format="" ag-id="0" ag-hash="-195540265" description="" owner-id="0" virtual="false" hidden="false"></parameter>
	<parameter name="shirina" caption="Ширина" type="integer" multiple="false" domain="" format="" ag-id="0" ag-hash="2061610206" description="см" owner-id="0" virtual="false" hidden="false"></parameter>
	<parameter name="sostav" caption="Состав" type="string" multiple="false" domain="" format="" ag-id="0" ag-hash="-896563534" description="" owner-id="0" virtual="false" hidden="false"></parameter>
	<parameter name="osobye_svoistva" caption="Особые свойства" type="string" multiple="false" domain="" format="" ag-id="0" ag-hash="1606100613" description="" owner-id="0" virtual="false" hidden="false"></parameter>
	<parameter name="svetopronitsaemost" caption="Светопроницаемость" type="integer" multiple="false" domain="" format="" ag-id="0" ag-hash="-1091719983" description="%" owner-id="0" virtual="false" hidden="false"></parameter>
	<parameter name="prozrachnost" caption="Прозрачность" type="double" multiple="false" domain="" format="" ag-id="0" ag-hash="1013208867" description="" owner-id="0" virtual="false" hidden="false"></parameter>
	<parameter name="plotnost" caption="Плотность" type="double" multiple="false" domain="" format="" ag-id="0" ag-hash="-2019236797" description="гр/м²" owner-id="0" virtual="false" hidden="false"></parameter>
	<parameter name="iznosostoikost" caption="Износостойкость" type="double" multiple="false" domain="" format="" ag-id="0" ag-hash="-1737542706" description="" owner-id="0" virtual="false" hidden="false"></parameter>
	<parameter name="risunok" caption="Рисунок" type="string" multiple="false" domain="" format="" ag-id="0" ag-hash="1212065105" description="" owner-id="0" virtual="false" hidden="false"></parameter>
	<parameter name="stil" caption="Стиль" type="string" multiple="false" domain="" format="" ag-id="0" ag-hash="3540804" description="" owner-id="0" virtual="false" hidden="false"></parameter>
	<parameter name="napravlenie_risunka" caption="Направление рисунка" type="double" multiple="false" domain="" format="" ag-id="0" ag-hash="-391113005" description="" owner-id="0" virtual="false" hidden="false"></parameter>
	<parameter name="rapport_gorizontalnyi" caption="Раппорт горизонтальный" type="double" multiple="false" domain="" format="" ag-id="0" ag-hash="1451310460" description="" owner-id="0" virtual="false" hidden="false"></parameter>
	<parameter name="rapport_vertikalnyi" caption="Раппорт вертикальный" type="double" multiple="false" domain="" format="" ag-id="0" ag-hash="233759011" description="" owner-id="0" virtual="false" hidden="false"></parameter>
	<parameter name="bordyur" caption="Бордюр" type="double" multiple="false" domain="" format="" ag-id="0" ag-hash="67263799" description="" owner-id="0" virtual="false" hidden="false"></parameter>
	<parameter name="vysota_bordyura" caption="Высота бордюра" type="double" multiple="false" domain="" format="" ag-id="0" ag-hash="821902813" description="" owner-id="0" virtual="false" hidden="false"></parameter>
	<parameter name="rapport_bordyura" caption="Раппорт бордюра" type="double" multiple="false" domain="" format="" ag-id="0" ag-hash="-2142819961" description="" owner-id="0" virtual="false" hidden="false"></parameter>
	<parameter name="utyagelitel" caption="Утяжелитель" type="double" multiple="false" domain="" format="" ag-id="0" ag-hash="697704345" description="" owner-id="0" virtual="false" hidden="false"></parameter>
	<parameter name="stirka" caption="Стирка" type="string" multiple="false" domain="" format="" ag-id="0" ag-hash="-892245472" description="" owner-id="0" virtual="false" hidden="false"></parameter>
	<parameter name="otgim" caption="Отжим" type="string" multiple="false" domain="" format="" ag-id="0" ag-hash="106068934" description="" owner-id="0" virtual="false" hidden="false"></parameter>
	<parameter name="sushka" caption="Сушка" type="string" multiple="false" domain="" format="" ag-id="0" ag-hash="-891033651" description="" owner-id="0" virtual="false" hidden="false"></parameter>
	<parameter name="glagka" caption="Глажка" type="string" multiple="false" domain="" format="" ag-id="0" ag-hash="-1243432351" description="" owner-id="0" virtual="false" hidden="false"></parameter>
	<parameter name="otbelivanie" caption="Отбеливание" type="string" multiple="false" domain="" format="" ag-id="0" ag-hash="158623290" description="" owner-id="0" virtual="false" hidden="false"></parameter>
	<parameter name="himchistka" caption="Химчистка" type="string" multiple="false" domain="" format="" ag-id="0" ag-hash="1967533327" description="" owner-id="0" virtual="false" hidden="false"></parameter>
	<parameter name="akvachistka" caption="Аквачистка" type="double" multiple="false" domain="" format="" ag-id="0" ag-hash="1706411046" description="" owner-id="0" virtual="false" hidden="false"></parameter>
</item>
<!--END_pt3-->

<!--START_ptz-->
<item name="ptz" caption="Ткани шаблоны" key="" virtual="false" user-def="true" description="" super="params *" ag-id="1823" ag-hash="111350">
	<parameter name="vid" caption="Вид" type="string" multiple="false" domain="" format="" ag-id="0" ag-hash="116753" description="" owner-id="0" virtual="false" hidden="false"></parameter>
	<parameter name="kategoriya" caption="Категория" type="string" multiple="false" domain="" format="" ag-id="0" ag-hash="-275590802" description="" owner-id="0" virtual="false" hidden="false"></parameter>
	<parameter name="kollektsiya" caption="Коллекция" type="string" multiple="false" domain="" format="" ag-id="0" ag-hash="592508680" description="" owner-id="0" virtual="false" hidden="false"></parameter>
	<parameter name="strana" caption="Страна" type="string" multiple="false" domain="" format="" ag-id="0" ag-hash="-891993597" description="" owner-id="0" virtual="false" hidden="false"></parameter>
	<parameter name="brend" caption="Бренд" type="double" multiple="false" domain="" format="" ag-id="0" ag-hash="94001803" description="" owner-id="0" virtual="false" hidden="false"></parameter>
	<parameter name="artikul" caption="Артикул" type="integer" multiple="false" domain="" format="" ag-id="0" ag-hash="-732369892" description="" owner-id="0" virtual="false" hidden="false"></parameter>
	<parameter name="tsvet" caption="Цвет" type="string" multiple="false" domain="" format="" ag-id="0" ag-hash="110671046" description="" owner-id="0" virtual="false" hidden="false"></parameter>
	<parameter name="tsvetovoi_ottenok" caption="Цветовой оттенок" type="string" multiple="false" domain="" format="" ag-id="0" ag-hash="2026120060" description="" owner-id="0" virtual="false" hidden="false"></parameter>
	<parameter name="parametry_tsveta" caption="Параметры цвета" type="string" multiple="false" domain="" format="" ag-id="0" ag-hash="-195540265" description="" owner-id="0" virtual="false" hidden="false"></parameter>
	<parameter name="shirina" caption="Ширина" type="integer" multiple="false" domain="" format="" ag-id="0" ag-hash="2061610206" description="см" owner-id="0" virtual="false" hidden="false"></parameter>
	<parameter name="sostav" caption="Состав" type="string" multiple="false" domain="" format="" ag-id="0" ag-hash="-896563534" description="" owner-id="0" virtual="false" hidden="false"></parameter>
	<parameter name="osobye_svoistva" caption="Особые свойства" type="string" multiple="false" domain="" format="" ag-id="0" ag-hash="1606100613" description="" owner-id="0" virtual="false" hidden="false"></parameter>
	<parameter name="svetopronitsaemost" caption="Светопроницаемость" type="double" multiple="false" domain="" format="" ag-id="0" ag-hash="-1091719983" description="%" owner-id="0" virtual="false" hidden="false"></parameter>
	<parameter name="prozrachnost" caption="Прозрачность" type="string" multiple="false" domain="" format="" ag-id="0" ag-hash="1013208867" description="" owner-id="0" virtual="false" hidden="false"></parameter>
	<parameter name="plotnost" caption="Плотность" type="double" multiple="false" domain="" format="" ag-id="0" ag-hash="-2019236797" description="гр/м²" owner-id="0" virtual="false" hidden="false"></parameter>
	<parameter name="iznosostoikost" caption="Износостойкость" type="double" multiple="false" domain="" format="" ag-id="0" ag-hash="-1737542706" description="" owner-id="0" virtual="false" hidden="false"></parameter>
	<parameter name="risunok" caption="Рисунок" type="string" multiple="false" domain="" format="" ag-id="0" ag-hash="1212065105" description="" owner-id="0" virtual="false" hidden="false"></parameter>
	<parameter name="stil" caption="Стиль" type="string" multiple="false" domain="" format="" ag-id="0" ag-hash="3540804" description="" owner-id="0" virtual="false" hidden="false"></parameter>
	<parameter name="napravlenie_risunka" caption="Направление рисунка" type="double" multiple="false" domain="" format="" ag-id="0" ag-hash="-391113005" description="" owner-id="0" virtual="false" hidden="false"></parameter>
	<parameter name="rapport_gorizontalnyi" caption="Раппорт горизонтальный" type="double" multiple="false" domain="" format="" ag-id="0" ag-hash="1451310460" description="" owner-id="0" virtual="false" hidden="false"></parameter>
	<parameter name="rapport_vertikalnyi" caption="Раппорт вертикальный" type="double" multiple="false" domain="" format="" ag-id="0" ag-hash="233759011" description="" owner-id="0" virtual="false" hidden="false"></parameter>
	<parameter name="bordyur" caption="Бордюр" type="double" multiple="false" domain="" format="" ag-id="0" ag-hash="67263799" description="" owner-id="0" virtual="false" hidden="false"></parameter>
	<parameter name="vysota_bordyura" caption="Высота бордюра" type="double" multiple="false" domain="" format="" ag-id="0" ag-hash="821902813" description="" owner-id="0" virtual="false" hidden="false"></parameter>
	<parameter name="rapport_bordyura" caption="Раппорт бордюра" type="double" multiple="false" domain="" format="" ag-id="0" ag-hash="-2142819961" description="" owner-id="0" virtual="false" hidden="false"></parameter>
	<parameter name="utyagelitel" caption="Утяжелитель" type="string" multiple="false" domain="" format="" ag-id="0" ag-hash="697704345" description="" owner-id="0" virtual="false" hidden="false"></parameter>
	<parameter name="stirka" caption="Стирка" type="double" multiple="false" domain="" format="" ag-id="0" ag-hash="-892245472" description="" owner-id="0" virtual="false" hidden="false"></parameter>
	<parameter name="otgim" caption="Отжим" type="double" multiple="false" domain="" format="" ag-id="0" ag-hash="106068934" description="" owner-id="0" virtual="false" hidden="false"></parameter>
	<parameter name="sushka" caption="Сушка" type="double" multiple="false" domain="" format="" ag-id="0" ag-hash="-891033651" description="" owner-id="0" virtual="false" hidden="false"></parameter>
	<parameter name="glagka" caption="Глажка" type="double" multiple="false" domain="" format="" ag-id="0" ag-hash="-1243432351" description="" owner-id="0" virtual="false" hidden="false"></parameter>
	<parameter name="otbelivanie" caption="Отбеливание" type="double" multiple="false" domain="" format="" ag-id="0" ag-hash="158623290" description="" owner-id="0" virtual="false" hidden="false"></parameter>
	<parameter name="himchistka" caption="Химчистка" type="double" multiple="false" domain="" format="" ag-id="0" ag-hash="1967533327" description="" owner-id="0" virtual="false" hidden="false"></parameter>
	<parameter name="akvachistka" caption="Аквачистка" type="double" multiple="false" domain="" format="" ag-id="0" ag-hash="1706411046" description="" owner-id="0" virtual="false" hidden="false"></parameter>
</item>
<!--END_ptz-->
<!--EXP--></model>